FQTool-1.4.data/scripts/fqtool
FQTool-1.4.dist-info/DESCRIPTION.rst
FQTool-1.4.dist-info/METADATA
FQTool-1.4.dist-info/RECORD
FQTool-1.4.dist-info/WHEEL
FQTool-1.4.dist-info/metadata.json
FQTool-1.4.dist-info/top_level.txt
src/ArgParser.py
src/FQParser.py
src/__init__.py
