Metadata-Version: 2.0
Name: FQTool
Version: 1.4
Summary: Tool to parse and filter FASTQ files
Home-page: https://github.com/mistrello96/FQTool
Author: Matteo Mistri, Bruno Palazzi, Lorenzo Soligo
Author-email: slg.lnz96@icloud.com
License: GNU GPLv3
Download-URL: https://github.com/mistrello96/FQTool/archive/1.4.tar.gz
Keywords: fastq,read,bioinformatics,parser
Platform: UNKNOWN
